design/fifo_mem.v
module fifo_mem#(parameter WIDTH=8,DEPTH=8,PTR_WIDTH=4)
  (input wclk, input w_en,
   input rclk, input r_en,
   input [PTR_WIDTH-1:0] b_rd_ptr,b_wr_ptr,
   input full, empty,
   input [WIDTH-1:0] d_in,
   output reg [WIDTH-1:0] d_out
  );
  
  reg [WIDTH-1:0] fifo [DEPTH];
  
  always@(posedge rclk) begin
    if(r_en & !empty) begin
      d_out<=fifo[b_rd_ptr[PTR_WIDTH-2:0]];
    end
  end
  
  always@(posedge wclk) begin
    if(w_en & !full)
      fifo[b_wr_ptr[PTR_WIDTH-2:0]] <= d_in;
  end
endmodule

design/write_ptr_handler.v
module wr_ptr_handler #(parameter WIDTH = 4)(input wclk,
                      input wrst,
                      input w_en,
                      input [WIDTH-1:0] g_rd_ptr_sync,//double flopped gray rd ptr
                      output reg full,
                      output reg [WIDTH-1:0] b_wr_ptr, //binary write pointer
                      output reg [WIDTH-1:0] g_wr_ptr //gray write pointer
                     );
  
  wire wfull;
  
  wire [WIDTH-1:0] b_wr_ptr_nxt = b_wr_ptr+(w_en&!full);
  wire [WIDTH-1:0] g_wr_ptr_nxt = (b_wr_ptr_nxt>>1) ^ b_wr_ptr_nxt;
  
  
  assign wfull = (g_wr_ptr_nxt == {~g_rd_ptr_sync[WIDTH-1:WIDTH-2],g_rd_ptr_sync[WIDTH-3:0]});
  
  always@(posedge wclk) begin
    if(wrst) begin
      full<=0;
      b_wr_ptr<=0;
      g_wr_ptr<=0;
    end
    else begin
      full<=wfull;
      b_wr_ptr<=b_wr_ptr_nxt;
      g_wr_ptr<=g_wr_ptr_nxt;
    end
  end
  
endmodule

design/read_ptr_handler.v
module rd_ptr_handler#(parameter WIDTH=4)(input rclk,
                      input r_rst,
                      input [WIDTH-1:0] g_wr_ptr_sync,
                      input r_en,
                      output reg [WIDTH-1:0] b_rd_ptr,
                      output reg [WIDTH-1:0] g_rd_ptr,
                      output reg empty
                                         );
  wire [WIDTH-1:0] b_rd_ptr_nxt,g_rd_ptr_nxt;
  wire rempty;
  
  assign b_rd_ptr_nxt = b_rd_ptr + (r_en && !empty);
  assign g_rd_ptr_nxt = (b_rd_ptr_nxt>>1) ^ b_rd_ptr_nxt;
  assign rempty = g_wr_ptr_sync==g_rd_ptr_nxt;
  
  always@(posedge rclk) begin
    if(r_rst) begin
      empty<=1'b1;
      b_rd_ptr<=0;
      g_rd_ptr<=0;
    end
    else begin
      empty<=rempty;
      b_rd_ptr<=b_rd_ptr_nxt;
      g_rd_ptr<=g_rd_ptr_nxt;
    end
  end
  
endmodule

design/synchroniser.v
module synchroniser#(parameter WIDTH=4)
  (input clk, rst,
   input [WIDTH-1:0] d_in,
   output reg [WIDTH-1:0] d_out
  );
  
  reg [WIDTH-1:0] q1;
  
  always@(posedge clk) begin
    if(rst) begin
      q1<=0;
      d_out<=0;
    end
    else begin
      q1<=d_in;
      d_out<=q1;
    end
  end
  
endmodule

design/async_fifo_wrapper.v
`include "synchroniser.v"
`include "read_ptr_handler.v"
`include "write_ptr_handler.v"
`include "fifo_mem.v"
module async_fifo_top#(parameter WIDTH=8,DEPTH=8)
  (input wclk,wrst,
   input rclk,r_rst,
   input w_en,r_en,
   input [WIDTH-1:0] d_in,
   output [WIDTH-1:0] d_out,
   output empty,full);
  
  parameter PTR_WIDTH = $clog2(DEPTH)+1;
  
  
  wire [PTR_WIDTH-1:0] g_rd_ptr,g_rd_ptr_sync,g_wr_ptr,g_wr_ptr_sync,
  					 b_rd_ptr,b_rd_ptr_sync,b_wr_ptr,b_wr_ptr_sync;
  
  
  synchroniser #(.WIDTH(PTR_WIDTH)) 
  			   r_sync(.clk(rclk),
                      .rst(r_rst),
                      .d_in(g_wr_ptr),
                      .d_out(g_wr_ptr_sync)
                     );
  
  synchroniser #(.WIDTH(PTR_WIDTH)) 
  			   w_sync(.clk(wclk),
                      .rst(wrst),
                      .d_in(g_rd_ptr),
                      .d_out(g_rd_ptr_sync)
                     );
  
  rd_ptr_handler #(.WIDTH(PTR_WIDTH)) 
   				read_hand (.rclk(rclk),
                           .r_rst(r_rst),
                           .g_wr_ptr_sync(g_wr_ptr_sync),
                           .r_en(r_en),
                           .b_rd_ptr(b_rd_ptr),
                           .g_rd_ptr(g_rd_ptr),
                           .empty(empty)
                          );
  
  wr_ptr_handler #(.WIDTH(PTR_WIDTH)) 
  	  			write_hand (.wclk(wclk),
                            .wrst(wrst),
                            .w_en(w_en),
                            .g_rd_ptr_sync(g_rd_ptr_sync),
                            .full(full),
                            .b_wr_ptr(b_wr_ptr),
                            .g_wr_ptr(g_wr_ptr)
                           );
 
  fifo_mem #(.WIDTH(WIDTH), .DEPTH(DEPTH), .PTR_WIDTH(PTR_WIDTH)) 
  		   memory(.wclk(wclk), .w_en(w_en),
                  .rclk(rclk), .r_en(r_en),
                  .b_rd_ptr(b_rd_ptr),
                  .b_wr_ptr(b_wr_ptr),
                  .full(full), .empty(empty),
                  .d_in(d_in),
                  .d_out(d_out)
                 );
  
  
endmodule

testbench/tb_async_fifo.v
module tb_async_fifo #(parameter WIDTH =8, DEPTH=8)();
  reg wclk,rclk,wrst,r_rst,w_en,r_en;
  reg [WIDTH-1:0] d_in;
  wire [WIDTH-1:0] d_out;
  wire empty,full;
  
  
  //write clk
  initial begin
    wclk = 0;  
    forever #5 wclk = ~wclk;
  end
  
  //read clk
  initial begin
    rclk = 0;
    forever #10 rclk = ~rclk;
  end
  
  //module inst
  async_fifo_top #(.WIDTH(WIDTH), .DEPTH(DEPTH)) 
  DUT(.wclk(wclk), .wrst(wrst), .rclk(rclk),
      .r_rst(r_rst),
      .w_en(w_en),
      .r_en(r_en),
      .d_in(d_in),
      .d_out(d_out),
      .empty(empty),
      .full(full)
     );
  
  
  //write reset
  task w_reset;
    begin
      wrst=1'b1;
      repeat(2)@(posedge wclk);
      @(negedge wclk);
      wrst = 0;
      @(posedge wclk);
      #1;
    end
  endtask
  
  //read reset
  task r_reset;
    begin
      r_rst=1'b1;
      repeat(2)@(posedge rclk);
      @(negedge rclk);
      r_rst = 0;
      @(posedge rclk);
      #1;
    end
  endtask
  
  
  //write op
  task write;
    input [WIDTH-1:0] data;
    begin
      @(negedge wclk)
      if(!full) begin
        $display("--WRITE OPERATION--");

        @(negedge wclk);
        d_in = data;
        w_en = 1'b1;

        @(posedge wclk);
        #1;
        w_en=0;
        d_in = 0;
        
        if(data == DUT.memory.fifo[DUT.read_hand.b_rd_ptr])
          $display("Successfully written ");
        else
          $display("Unsuccessfully written ");
      end
      else
        $display("FIFO full");
      
    end
  endtask
  
  task read;
    begin
      @(negedge rclk)
      if(!empty) begin
        $display("--READ OPERATION--");

        repeat(1)@(negedge rclk);
        
        r_en = 1'b1;
        repeat(1)@(posedge rclk);
        #1;
        
        r_en=0;
        repeat(1)@(posedge rclk);
        #1;
        
        $display("--Read %b from FIFO--", d_out);
      end
      else
        $display("FIFO empty");
        
    end
  endtask
    
      
      
      
      
  
  initial begin
    wrst=1;
    r_rst=1;
    w_en=0;
    r_en=0;
    $dumpfile("image.vcd");
    $dumpvars(0, tb_async_fifo);
    
    //reset
    fork
      w_reset();
      r_reset();
    join
    
    write(8'hFF);
    write(8'd7);
    
    repeat(4)@(posedge rclk);
    
    //$display(DUT.memory.fifo[DUT.read_hand.b_rd_ptr]);
    
    read();
    read();
    
    #10
    
    $finish();
  end  
  
endmodule

testbench/image.vcd
$date
	Fri Jul 17 01:02:17 2026
$end
$version
	Icarus Verilog
$end
$timescale
	1s
$end
$scope module tb_async_fifo $end
$var wire 1 ! full $end
$var wire 1 " empty $end
$var wire 8 # d_out [7:0] $end
$var parameter 32 $ DEPTH $end
$var parameter 32 % WIDTH $end
$var reg 8 & d_in [7:0] $end
$var reg 1 ' r_en $end
$var reg 1 ( r_rst $end
$var reg 1 ) rclk $end
$var reg 1 * w_en $end
$var reg 1 + wclk $end
$var reg 1 , wrst $end
$scope module DUT $end
$var wire 8 - d_in [7:0] $end
$var wire 1 ' r_en $end
$var wire 1 ( r_rst $end
$var wire 1 ) rclk $end
$var wire 1 * w_en $end
$var wire 1 + wclk $end
$var wire 1 , wrst $end
$var wire 4 . g_wr_ptr_sync [3:0] $end
$var wire 4 / g_wr_ptr [3:0] $end
$var wire 4 0 g_rd_ptr_sync [3:0] $end
$var wire 4 1 g_rd_ptr [3:0] $end
$var wire 1 ! full $end
$var wire 1 " empty $end
$var wire 8 2 d_out [7:0] $end
$var wire 4 3 b_wr_ptr [3:0] $end
$var wire 4 4 b_rd_ptr [3:0] $end
$var parameter 32 5 DEPTH $end
$var parameter 33 6 PTR_WIDTH $end
$var parameter 32 7 WIDTH $end
$scope module memory $end
$var wire 8 8 d_in [7:0] $end
$var wire 1 ' r_en $end
$var wire 1 ) rclk $end
$var wire 1 * w_en $end
$var wire 1 + wclk $end
$var wire 1 ! full $end
$var wire 1 " empty $end
$var wire 4 9 b_wr_ptr [3:0] $end
$var wire 4 : b_rd_ptr [3:0] $end
$var parameter 32 ; DEPTH $end
$var parameter 33 < PTR_WIDTH $end
$var parameter 32 = WIDTH $end
$var reg 8 > d_out [7:0] $end
$upscope $end
$scope module r_sync $end
$var wire 1 ) clk $end
$var wire 1 ( rst $end
$var wire 4 ? d_in [3:0] $end
$var parameter 33 @ WIDTH $end
$var reg 4 A d_out [3:0] $end
$var reg 4 B q1 [3:0] $end
$upscope $end
$scope module read_hand $end
$var wire 4 C g_rd_ptr_nxt [3:0] $end
$var wire 4 D g_wr_ptr_sync [3:0] $end
$var wire 1 ' r_en $end
$var wire 1 ( r_rst $end
$var wire 1 ) rclk $end
$var wire 1 E rempty $end
$var wire 4 F b_rd_ptr_nxt [3:0] $end
$var parameter 33 G WIDTH $end
$var reg 4 H b_rd_ptr [3:0] $end
$var reg 1 " empty $end
$var reg 4 I g_rd_ptr [3:0] $end
$upscope $end
$scope module w_sync $end
$var wire 1 + clk $end
$var wire 4 J d_in [3:0] $end
$var wire 1 , rst $end
$var parameter 33 K WIDTH $end
$var reg 4 L d_out [3:0] $end
$var reg 4 M q1 [3:0] $end
$upscope $end
$scope module write_hand $end
$var wire 4 N g_rd_ptr_sync [3:0] $end
$var wire 4 O g_wr_ptr_nxt [3:0] $end
$var wire 1 * w_en $end
$var wire 1 + wclk $end
$var wire 1 , wrst $end
$var wire 1 P wfull $end
$var wire 4 Q b_wr_ptr_nxt [3:0] $end
$var parameter 33 R WIDTH $end
$var reg 4 S b_wr_ptr [3:0] $end
$var reg 1 ! full $end
$var reg 4 T g_wr_ptr [3:0] $end
$upscope $end
$upscope $end
$scope task r_reset $end
$upscope $end
$scope task read $end
$upscope $end
$scope task w_reset $end
$upscope $end
$scope task write $end
$var reg 8 U data [7:0] $end
$upscope $end
$upscope $end
$enddefinitions $end
$comment Show the parameter values. $end
$dumpall
b100 R
b100 K
b100 G
b100 @
b1000 =
b100 <
b1000 ;
b1000 7
b100 6
b1000 5
b1000 %
b1000 $
$end
#0
$dumpvars
bx U
bx T
bx S
bx Q
xP
bx O
bx N
bx M
bx L
bx J
bx I
bx H
bx F
xE
bx D
bx C
bx B
bx A
bx ?
bx >
bx :
bx 9
bx 8
bx 4
bx 3
bx 2
bx 1
bx 0
bx /
bx .
bx -
1,
0+
0*
0)
1(
0'
bx &
bx #
x"
x!
$end
#5
0P
b0 O
b0 0
b0 L
b0 N
b0 M
b0 /
b0 ?
b0 T
b0 Q
b0 3
b0 9
b0 S
0!
1+
#10
1E
b0 C
b0 .
b0 A
b0 D
b0 B
b0 1
b0 I
b0 J
b0 F
b0 4
b0 :
b0 H
1"
0+
1)
#15
1+
#20
0,
0+
0)
#25
1+
#30
0+
1)
#35
1+
#40
0(
0+
0)
#45
1+
#50
0+
1)
#51
b11111111 U
#55
1+
#60
0+
0)
#65
1+
#70
b1 O
b1 Q
1*
b11111111 &
b11111111 -
b11111111 8
0+
1)
#75
b11 O
b1 /
b1 ?
b1 T
b10 Q
b1 3
b1 9
b1 S
1+
#76
b1 O
b1 Q
b111 U
b0 &
b0 -
b0 8
0*
#80
0+
0)
#85
1+
#90
b1 B
b11 O
b10 Q
1*
b111 &
b111 -
b111 8
0+
1)
#95
b10 O
b11 /
b11 ?
b11 T
b11 Q
b10 3
b10 9
b10 S
1+
#96
b11 O
b10 Q
b0 &
b0 -
b0 8
0*
#100
0+
0)
#105
1+
#110
0E
b1 .
b1 A
b1 D
b11 B
0+
1)
#115
1+
#120
0+
0)
#125
1+
#130
b11 .
b11 A
b11 D
0"
0+
1)
#135
1+
#140
0+
0)
#145
1+
#150
0+
1)
#155
1+
#160
0+
0)
#165
1+
#170
0+
1)
#175
1+
#180
0+
0)
#185
1+
#190
0+
1)
#195
1+
#200
b1 C
b1 F
1'
0+
0)
#205
1+
#210
1E
b11 C
b1 1
b1 I
b1 J
b10 F
b1 4
b1 :
b1 H
b11111111 #
b11111111 2
b11111111 >
0+
1)
#211
0E
b1 C
b1 F
0'
#215
b1 M
1+
#220
0+
0)
#225
b1 0
b1 L
b1 N
1+
#230
0+
1)
#235
1+
#240
0+
0)
#245
1+
#250
0+
1)
#255
1+
#260
1E
b11 C
b10 F
1'
0+
0)
#265
1+
#270
b111 #
b111 2
b111 >
b11 1
b11 I
b11 J
b10 F
b10 4
b10 :
b10 H
1"
0+
1)
#271
0'
#275
b11 M
1+
#280
0+
0)
#285
b11 0
b11 L
b11 N
1+
